{
  "source_image": "dataset/chessred2k/images/28/G028_IMG100.jpg",
  "corners": [
    {
      "x": 668,
      "y": 918
    },
    {
      "x": 2250,
      "y": 872
    },
    {
      "x": 2614,
      "y": 2185
    },
    {
      "x": 380,
      "y": 2247
    }
  ],
  "candidates": [
    {
      "x": 1053,
      "y": 1030
    },
    {
      "x": 1064,
      "y": 903
    },
    {
      "x": 1234,
      "y": 1798
    },
    {
      "x": 1240,
      "y": 1616
    },
    {
      "x": 1484,
      "y": 1786
    },
    {
      "x": 1491,
      "y": 1986
    }
  ]
}