{
  "source_image": "dataset/chessred2k/images/42/G042_IMG065.jpg",
  "corners": [
    {
      "x": 399,
      "y": 1102
    },
    {
      "x": 1934,
      "y": 744
    },
    {
      "x": 2656,
      "y": 1992
    },
    {
      "x": 841,
      "y": 2540
    }
  ],
  "candidates": [
    {
      "x": 2757,
      "y": 30
    },
    {
      "x": 2761,
      "y": 46
    },
    {
      "x": 2766,
      "y": 63
    },
    {
      "x": 2771,
      "y": 84
    },
    {
      "x": 2777,
      "y": 107
    },
    {
      "x": 2783,
      "y": 134
    },
    {
      "x": 2787,
      "y": 149
    },
    {
      "x": 2791,
      "y": 166
    },
    {
      "x": 2796,
      "y": 186
    },
    {
      "x": 2800,
      "y": 201
    },
    {
      "x": 2807,
      "y": 32
    },
    {
      "x": 2810,
      "y": 48
    },
    {
      "x": 2813,
      "y": 65
    },
    {
      "x": 2816,
      "y": 84
    },
    {
      "x": 2820,
      "y": 107
    },
    {
      "x": 2823,
      "y": 127
    },
    {
      "x": 2826,
      "y": 143
    },
    {
      "x": 2830,
      "y": 167
    },
    {
      "x": 2834,
      "y": 189
    },
    {
      "x": 2837,
      "y": 204
    }
  ]
}