{
  "source_image": "dataset/chessred2k/images/99/G099_IMG070.jpg",
  "corners": [
    {
      "x": 1222,
      "y": 809
    },
    {
      "x": 2627,
      "y": 1147
    },
    {
      "x": 2163,
      "y": 2256
    },
    {
      "x": 441,
      "y": 1724
    }
  ],
  "candidates": [
    {
      "x": 1750,
      "y": 435
    },
    {
      "x": 1756,
      "y": 460
    },
    {
      "x": 1760,
      "y": 479
    },
    {
      "x": 1784,
      "y": 583
    },
    {
      "x": 1793,
      "y": 622
    },
    {
      "x": 2095,
      "y": 509
    },
    {
      "x": 2096,
      "y": 490
    },
    {
      "x": 2098,
      "y": 463
    },
    {
      "x": 2099,
      "y": 448
    },
    {
      "x": 2100,
      "y": 432
    },
    {
      "x": 2194,
      "y": 517
    },
    {
      "x": 2197,
      "y": 499
    },
    {
      "x": 2201,
      "y": 477
    },
    {
      "x": 2204,
      "y": 459
    },
    {
      "x": 2208,
      "y": 437
    }
  ]
}